LICENSE
MANIFEST.in
README
README.rst
README.upgrading.rst
RELEASE-NOTES.rst
django-sshkey-lookup
django-sshkey-lookup-all
django-sshkey-lookup-by-fingerprint
django-sshkey-lookup-by-username
lookup.py
lookup.sh
setup.py
django_sshkey/__init__.py
django_sshkey/admin.py
django_sshkey/forms.py
django_sshkey/models.py
django_sshkey/settings.py
django_sshkey/tests.py
django_sshkey/urls.py
django_sshkey/util.py
django_sshkey/views.py
django_sshkey.egg-info/PKG-INFO
django_sshkey.egg-info/SOURCES.txt
django_sshkey.egg-info/dependency_links.txt
django_sshkey.egg-info/entry_points.txt
django_sshkey.egg-info/not-zip-safe
django_sshkey.egg-info/requires.txt
django_sshkey.egg-info/top_level.txt
django_sshkey/migrations/0001_initial.py
django_sshkey/migrations/0002_resize_fingerprint.py
django_sshkey/migrations/__init__.py
django_sshkey/south_migrations/0001_initial.py
django_sshkey/south_migrations/0002_auto__add_field_userkey_last_used.py
django_sshkey/south_migrations/0003_auto__chg_field_userkey_last_modified__chg_field_userkey_fingerprint.py
django_sshkey/south_migrations/__init__.py
django_sshkey/templates.example/sshkey/add_key.html
django_sshkey/templates.example/sshkey/add_key.txt
django_sshkey/templates.example/sshkey/userkey_detail.html
django_sshkey/templates.example/sshkey/userkey_list.html