Metadata-Version: 1.1
Name: django-sshkey
Version: 2.5.0
Summary: Associates multiple SSH public keys with Django user accounts.
Home-page: https://github.com/ClemsonSoCUnix/django-sshkey
Author: Scott Duckworth
Author-email: sduckwo@clemson.edu
License: BSD
Platform: UNKNOWN
Classifier: Environment :: Web Environment
Classifier: Framework :: Django
Classifier: Intended Audience :: Developers
Classifier: License :: OSI Approved :: BSD License
Classifier: Operating System :: OS Independent
Classifier: Programming Language :: Python
Classifier: Programming Language :: Python :: 2.7
Classifier: Programming Language :: Python :: 3.3
Classifier: Programming Language :: Python :: 3.4
Classifier: Topic :: Internet :: WWW/HTTP
Classifier: Topic :: Internet :: WWW/HTTP :: Dynamic Content
